{
  "id": "home-page",
  "name": "home-page",
  "title": "首页文章列表",
  "description": "实现首页：PostList、PostCard、标签筛选",
  "status": "completed",
  "dev_type": null,
  "scope": null,
  "package": null,
  "priority": "P1",
  "creator": "cicada",
  "assignee": "cicada",
  "createdAt": "2026-06-24",
  "completedAt": "2026-06-24",
  "branch": null,
  "base_branch": "main",
  "worktree_path": null,
  "commit": null,
  "pr_url": null,
  "subtasks": [],
  "children": [],
  "parent": null,
  "relatedFiles": [],
  "notes": "",
  "meta": {}
}